django_mcp_integration/__init__.py
django_mcp_integration/__version__.py
django_mcp_integration/admin.py
django_mcp_integration/apps.py
django_mcp_integration/crypto.py
django_mcp_integration/exceptions.py
django_mcp_integration/managers.py
django_mcp_integration/models.py
django_mcp_integration/core/__init__.py
django_mcp_integration/core/conf.py
django_mcp_integration/core/discovery.py
django_mcp_integration/core/registry.py
django_mcp_integration/core/server.py
django_mcp_integration/decorators/__init__.py
django_mcp_integration/decorators/tools.py
django_mcp_integration/handlers/__init__.py
django_mcp_integration/handlers/asgi.py
django_mcp_integration/management/__init__.py
django_mcp_integration/management/commands/__init__.py
django_mcp_integration/middleware/__init_.py
django_mcp_integration/middleware/tool_middeware.py
django_mcp_integration/permissions/__init__.py
django_mcp_integration/permissions/base.py
django_mcp_integration/permissions/handlers.py
django_mcp_integration/utils/__init__.py
django_mcp_integration/utils/logging.py
django_mcp_integration/utils/types.py
django_mcp_integration-1.0.5.dist-info/METADATA
django_mcp_integration-1.0.5.dist-info/WHEEL
django_mcp_integration-1.0.5.dist-info/top_level.txt
django_mcp_integration-1.0.5.dist-info/RECORD
