Metadata-Version: 2.4
Name: django-mcp-integration
Version: 1.0.5
Summary: Intégration MCP pour Django via FastMCP
Author-email: Cissé Anzoumana <anzcisse1@gmail.com>
License: MIT
Project-URL: Homepage, https://github.com/mosco23/django-mcp-integration
Project-URL: Documentation, https://github.com/mosco23/django-mcp-integration#readme
Project-URL: Bug Tracker, https://github.com/mosco23/django-mcp-integration/issues
Keywords: django,mcp,server,fastmcp,asgi,ai
Classifier: Development Status :: 4 - Beta
Classifier: Framework :: Django
Classifier: Framework :: Django :: 3.2
Classifier: Framework :: Django :: 4.0
Classifier: Framework :: Django :: 4.1
Classifier: Framework :: Django :: 4.2
Classifier: Framework :: Django :: 5.0
Classifier: Intended Audience :: Developers
Classifier: License :: OSI Approved :: MIT License
Classifier: Operating System :: OS Independent
Classifier: Programming Language :: Python :: 3
Classifier: Programming Language :: Python :: 3.8
Classifier: Programming Language :: Python :: 3.9
Classifier: Programming Language :: Python :: 3.10
Classifier: Programming Language :: Python :: 3.11
Classifier: Programming Language :: Python :: 3.12
Classifier: Programming Language :: Python :: 3.13
Classifier: Topic :: Internet :: WWW/HTTP
Classifier: Topic :: Software Development :: Libraries :: Python Modules
Requires-Python: >=3.8
Requires-Dist: Django>=3.2
Requires-Dist: fastmcp>=2.13.0
Requires-Dist: uvicorn[standard]>=0.20.0
Requires-Dist: httpx>=0.24.0
Provides-Extra: dev
Requires-Dist: black>=23.0.0; extra == "dev"
Requires-Dist: flake8>=6.0.0; extra == "dev"
Requires-Dist: pytest>=7.0.0; extra == "dev"
Requires-Dist: pytest-asyncio>=0.21.0; extra == "dev"
Requires-Dist: pytest-django>=4.5.0; extra == "dev"
